beanprice_br/__init__.py
beanprice_br/_cache.py
beanprice_br/_source.py
beanprice_br/fi.py
beanprice_br/tesouro_direto.py
beanprice_br-0.2.1.dist-info/LICENSE
beanprice_br-0.2.1.dist-info/METADATA
beanprice_br-0.2.1.dist-info/WHEEL
beanprice_br-0.2.1.dist-info/RECORD
