Metadata-Version: 2.1
Name: beanprice-br
Version: 0.2.1
Summary: Price sources for Brazilian commodities
License: ISC
Author: Gabriel Soldani
Author-email: gabriel@gabrielsoldani.com
Requires-Python: >=3.10,<4.0
Classifier: License :: OSI Approved
Classifier: Programming Language :: Python :: 3
Classifier: Programming Language :: Python :: 3.10
Classifier: Programming Language :: Python :: 3.11
Classifier: Programming Language :: Python :: 3.12
Requires-Dist: requests (>=2.31.0,<3.0.0)
